{
    "type": "FeatureCollection",
    "features": [
        {
            "type": "Feature",
            "geometry": {
                "type": "Polygon",
                "coordinates": [
                    [
                        [ 127.074504, 37.516542 ],
                        [ 127.074146, 37.516514 ],
                        [ 127.074329, 37.515605 ],
                        [ 127.074665, 37.515671 ]
                    ]
                ]
            },
            "properties": {
                "title": "Event Zone",
                "fillColor" : "ffc6dadd",
                "strokeColor": "ffc6daed",
                "lineWidth": 1,
                "type": "zone"
            }
        },
        {
            "type": "Feature",
            "geometry": {
                "type": "Polygon",
                "coordinates": [
                    [
                        [ 127.072867, 37.517277 ],
                        [ 127.072658, 37.517294 ],
                        [ 127.071972, 37.517207 ],
                        [ 127.072044, 37.516924 ],
                        [ 127.072470, 37.517043 ],
                        [ 127.072857, 37.517058 ]
                    ]
                ]
            },
            "properties": {
                "title": "Food & Beverage Zone",
                "fillColor" : "ffb2d9e5",
                "strokeColor": "ffb2d9f0",
                "lineWidth": 1,
                "type": "zone"
            }
        },
        {
            "type": "Feature",
            "geometry": {
                "type": "Polygon",
                "coordinates": [
                    [
                        [ 127.071381, 37.517674 ],
                        [ 127.071140, 37.517728 ],
                        [ 127.070918, 37.517686 ],
                        [ 127.070252, 37.517009 ],
                        [ 127.070189, 37.516743 ],
                        [ 127.070332, 37.516555 ],
                        [ 127.070863, 37.516555 ],
                        [ 127.071531, 37.517254 ],
                        [ 127.071541, 37.517504 ]
                    ]
                ]
            },
            "properties": {
                "title": "ID Verification",
                "fillColor" : "fff3c9c8",
                "strokeColor": "ffffc9c8",
                "lineWidth": 1,
                "type": "zone"
            }
        },
        {
            "type": "Feature",
            "geometry": {
                "type": "Polygon",
                "coordinates": [
                    [
                        [ 127.071115, 37.515279 ],
                        [ 127.070264, 37.515181 ],
                        [ 127.070392, 37.514377 ],
                        [ 127.071185, 37.514457 ]
                    ]
                ]
            },
            "properties": {
                "title": "Official MD",
                "fillColor" : "fffdac9b",
                "strokeColor": "fffdc09b",
                "lineWidth": 1,
                "type": "zone"
            }
        },
        {
            "type": "Feature",
            "geometry": {
                "type": "Polygon",
                "coordinates": [
                    [
                        [ 127.071178, 37.514427 ],
                        [ 127.070392, 37.514363 ],
                        [ 127.070450, 37.514002 ],
                        [ 127.071235, 37.514129 ]
                    ]
                ]
            },
            "properties": {
                "title": "Parking lot",
                "fillColor" : "ffe8c99b",
                "strokeColor": "ffe8db9b",
                "lineWidth": 1,
                "type": "Zone"
            }
        },
        {
            "type": "Feature",
            "geometry": {
                "type": "Polygon",
                "coordinates": [
                    [
                        [ 127.073175, 37.514645 ],
                        [ 127.072815, 37.514619 ],
                        [ 127.072825, 37.514373 ],
                        [ 127.073205, 37.514387 ]
                    ]
                ]
            },
            "properties": {
                "title": "Ticket Box",
                "fillColor" : "ffdde6d7",
                "strokeColor": "ffddf0d7",
                "lineWidth": 1,
                "type": "zone"
            }
        },
        {
            "type": "Feature",
            "geometry": {
                "type": "Point",
                "coordinates": [ 127.073016, 37.514511 ]
            },
            "properties": {
                "title": "Ticket Box",
                "type": "zone"
            }
        },
        
        {
            "type": "Feature",
            "geometry": {
                "type": "Point",
                "coordinates": [ 127.074429, 37.516459 ]
            },
            "properties": {
                "title": "KB Bank & Card",
                "subtitle": "Wait 5 minutes",
                "type": "bank"
            }
        },
        {
            "type": "Feature",
            "geometry": {
                "type": "Point",
                "coordinates": [ 127.074215, 37.516430 ]
            },
            "properties": {
                "title": "VT Cosmetic",
                "subtitle": "Wait 5 minutes",
                "type": "medical"
            }
        },
        {
            "type": "Feature",
            "geometry": {
                "type": "Point",
                "coordinates": [ 127.074371, 37.516311 ]
            },
            "properties": {
                "title": "Lotte Duty Free Shop",
                "subtitle": "Wait 5 minutes",
                "type": "photo"
            }
        },
        {
            "type": "Feature",
            "geometry": {
                "type": "Point",
                "coordinates": [ 127.074517, 37.516174 ]
            },
            "properties": {
                "title": "BTS Photo Studio",
                "subtitle": "Wait 10 minutes",
                "type": "photo"
            }
        },
        {
            "type": "Feature",
            "geometry": {
                "type": "Point",
                "coordinates": [ 127.074544, 37.516058 ]
            },
            "properties": {
                "title": "LOVE MYSELF",
                "subtitle": "Wait 5 minutes",
                "type": "event"
            }
        },
        {
            "type": "Feature",
            "geometry": {
                "type": "Point",
                "coordinates": [ 127.074368, 37.515945]
            },
            "properties": {
                "title": "Photo card Random Box",
                "subtitle": "Wait 5 minutes",
                "type": "photo"
            }
        },
        {
            "type": "Feature",
            "geometry": {
                "type": "Point",
                "coordinates": [ 127.074351, 37.515802 ]
            },
            "properties": {
                "title": "ARMY BOMB Pairing Booth",
                "subtitle": "Wait 15 minutes",
                "type": "shop"
            }
        },
        {
            "type": "Feature",
            "geometry": {
                "type": "Point",
                "coordinates": [ 127.074585, 37.515810 ]
            },
            "properties": {
                "title": "Photo Wall",
                "subtitle": "Wait 10 minutes",
                "type": "photo"
                
            }
        },
        {
            "type": "Feature",
            "geometry": {
                "type": "Point",
                "coordinates": [ 127.072747, 37.513932 ]
            },
            "properties": {
                "title": "Info & Lost & Found",
                "type": "information"
            }
        }
    ]
}
